{
  "type": "KPI",
  "classifiers": {
    "source": "KPIS",
    "category": "KPI",
    "domain": "RAN",
    "element-type": "cell",
    "technology": "LTE",
    "datasource": "pm"
  },
  "legend": {
    "type": "dynamic",
    "ascending": true,
    "size": true,
    "border": true,
    "fill": true,
    "range": []
  },
  "additionalFields": {},
  "preferred": false,
  "uuid": "4g_average_cqi",
  "name": "4g_average_cqi",
  "label": "LTE Average CQI",
  "docdb_id": "7814987c-e876-4e85-ad3a-aeea5117428e",
  "createdAt": "2023-07-07T09:14:08.654Z",
  "version_id": "1b104959-58ab-4a12-92b6-957b045973a1"
}